cxc_django/__init__.py
cxc_django/fields.py
cxc_django/mixins.py
cxc_django/response.py
cxc_django/viewsets.py
cxc_django-0.0.4.dist-info/DESCRIPTION.rst
cxc_django-0.0.4.dist-info/METADATA
cxc_django-0.0.4.dist-info/RECORD
cxc_django-0.0.4.dist-info/WHEEL
cxc_django-0.0.4.dist-info/metadata.json
cxc_django-0.0.4.dist-info/top_level.txt
