Metadata-Version: 2.0
Name: cxc-django
Version: 0.0.4
Summary: A django wrapper made by Xiaochen Cui
Home-page: https://github.com/XiaochenCui/cxc-django
Author: Xiaochen Cui
Author-email: jcnlcxc.new@gmail.com
License: GPLv3
Keywords: django
Platform: UNKNOWN
Classifier: Development Status :: 1 - Planning
Classifier: Intended Audience :: Developers
Classifier: Topic :: Software Development :: Libraries :: Python Modules
Classifier: License :: OSI Approved :: GNU General Public License v3 (GPLv3)
Classifier: Programming Language :: Python :: 3
Classifier: Programming Language :: Python :: 3.6
Classifier: Programming Language :: Python :: 3 :: Only
Requires-Dist: django
Requires-Dist: django-rest-framework
Requires-Dist: cxc-gis
